pyams_geoconverter/__init__.py
pyams_geoconverter/converter.py
pyams_geoconverter/include.py
pyams_geoconverter/interfaces.py
pyams_geoconverter/api/__init__.py
pyams_geoconverter/api/schema.py
pyams_geoconverter/doctests/README.rst
pyams_geoconverter/locales/pyams_geoconverter.pot
pyams_geoconverter/locales/fr/LC_MESSAGES/pyams_geoconverter.mo
pyams_geoconverter/locales/fr/LC_MESSAGES/pyams_geoconverter.po
pyams_geoconverter/tests/__init__.py
pyams_geoconverter/tests/test_utilsdocs.py
pyams_geoconverter/tests/test_utilsdocstrings.py
pyams_geoconverter-2.2.3.dist-info/LICENSE
pyams_geoconverter-2.2.3.dist-info/METADATA
pyams_geoconverter-2.2.3.dist-info/WHEEL
pyams_geoconverter-2.2.3.dist-info/namespace_packages.txt
pyams_geoconverter-2.2.3.dist-info/top_level.txt
pyams_geoconverter-2.2.3.dist-info/RECORD
