Metadata-Version: 2.1
Name: pyams-geoconverter
Version: 2.2.3
Summary: PyAMS converter for geospatial files
Home-page: https://pyams.readthedocs.io
Author: Thierry Florac
Author-email: tflorac@ulthar.net
License: ZPL
Keywords: Pyramid PyAMS
Classifier: License :: OSI Approved :: Zope Public License
Classifier: Development Status :: 4 - Beta
Classifier: Programming Language :: Python
Classifier: Framework :: Pyramid
Classifier: Topic :: Software Development :: Libraries :: Python Modules
Requires-Python: >=3.7
License-File: LICENSE
Requires-Dist: setuptools
Requires-Dist: colander
Requires-Dist: cornice
Requires-Dist: geopandas
Requires-Dist: pyams-file
Requires-Dist: pyams-security
Requires-Dist: pyams-utils
Requires-Dist: pyramid >=2.0.0
Provides-Extra: test
Requires-Dist: pyramid-zcml ; extra == 'test'
Requires-Dist: zope.exceptions ; extra == 'test'
